fasterai/__init__.py
fasterai/_modidx.py
fasterai/core/__init__.py
fasterai/core/all.py
fasterai/core/criteria.py
fasterai/core/granularity.py
fasterai/core/schedule.py
fasterai/distill/__init__.py
fasterai/distill/all.py
fasterai/distill/distillation_callback.py
fasterai/misc/__init__.py
fasterai/misc/all.py
fasterai/misc/bn_folding.py
fasterai/misc/cpu_optimizer.py
fasterai/misc/fc_decomposer.py
fasterai/prune/__init__.py
fasterai/prune/all.py
fasterai/prune/prune_callback.py
fasterai/prune/pruner.py
fasterai/quantize/__init__.py
fasterai/quantize/all.py
fasterai/quantize/quantize_callback.py
fasterai/quantize/quantizer.py
fasterai/regularize/__init__.py
fasterai/regularize/all.py
fasterai/regularize/regularize_callback.py
fasterai/sparse/__init__.py
fasterai/sparse/all.py
fasterai/sparse/sparsifier.py
fasterai/sparse/sparsify_callback.py
fasterai-0.2.7.dist-info/LICENSE
fasterai-0.2.7.dist-info/METADATA
fasterai-0.2.7.dist-info/WHEEL
fasterai-0.2.7.dist-info/entry_points.txt
fasterai-0.2.7.dist-info/top_level.txt
fasterai-0.2.7.dist-info/RECORD
