Metadata-Version: 2.1
Name: fasterai
Version: 0.2.7
Summary: A library to make neural networks lighter and faster with fastai
Home-page: https://github.com/FasterAI-Labs/fasterai/tree/master/
Author: Nathan Hubens
Author-email: nathan.hubens@gmail.com
License: Apache Software License 2.0
Keywords: Pruning
Classifier: Development Status :: 3 - Alpha
Classifier: Intended Audience :: Developers
Classifier: Natural Language :: English
Classifier: Programming Language :: Python :: 3.6
Classifier: Programming Language :: Python :: 3.7
Classifier: Programming Language :: Python :: 3.8
Classifier: Programming Language :: Python :: 3.9
Classifier: Programming Language :: Python :: 3.10
Classifier: License :: OSI Approved :: Apache Software License
Requires-Python: >=3.6
License-File: LICENSE
Requires-Dist: fastai >=2.2
Requires-Dist: torch-pruning >=1.2
Provides-Extra: dev
